[
  {
    "id": 1,
    "category": "فقه",
    "level": "صعب",
    "source": "غير محدد",
    "q": "من ترك الصلاة جاحداً لوجوبها وهو يعلم أنها فرض، فما حكمه عند جمهور العلماء؟",
    "a": [
      "فاسق مرتكب لكبيرة",
      "كافر",
      "مكروه فعله",
      "عاصٍ فقط"
    ],
    "c": 1
  },
  {
    "id": 2,
    "category": "فقه",
    "level": "سهل",
    "source": "غير محدد",
    "q": "أي العبادات التالية لا تجب إلا عند تحقق النصاب؟",
    "a": [
      "الصلاة",
      "الصيام",
      "الزكاة",
      "بر الوالدين"
    ],
    "c": 2
  },
  {
    "id": 3,
    "category": "فقه",
    "level": "سهل",
    "source": "غير محدد",
    "q": "ما الركن الذي لا يصح الوضوء بدونه؟",
    "a": [
      "التسمية",
      "غسل الوجه",
      "السواك",
      "دعاء الوضوء"
    ],
    "c": 1
  },
  {
    "id": 4,
    "category": "فقه",
    "level": "متوسط",
    "source": "غير محدد",
    "q": "إذا شك المصلي هل صلى ثلاث ركعات أم أربعاً ولم يترجح لديه شيء، فماذا يفعل؟",
    "a": [
      "يبني على اليقين وهو الأقل",
      "يعيد الصلاة مباشرة",
      "يبني على الأكثر",
      "يقطع الصلاة"
    ],
    "c": 0
  },
  {
    "id": 5,
    "category": "أصول فقه",
    "level": "صعب",
    "source": "غير محدد",
    "q": "ما الحكم الشرعي للأمر إذا ورد في القرآن أو السنة مجرداً من القرائن عند جمهور الأصوليين؟",
    "a": [
      "الاستحباب",
      "الإباحة",
      "الوجوب",
      "الكراهة"
    ],
    "c": 2
  },
  {
    "id": 6,
    "category": "فقه",
    "level": "سهل",
    "source": "غير محدد",
    "q": "أي الأصناف التالية تجب فيه زكاة بهيمة الأنعام إذا بلغ النصاب؟",
    "a": [
      "الخيل المعدة للركوب فقط",
      "الإبل",
      "الحمير",
      "الطيور"
    ],
    "c": 1
  },
  {
    "id": 7,
    "category": "فقه",
    "level": "سهل",
    "source": "غير محدد",
    "q": "ما حكم صيام يوم عيد الفطر؟",
    "a": [
      "واجب",
      "مستحب",
      "مكروه",
      "محرم"
    ],
    "c": 3
  },
  {
    "id": 8,
    "category": "فقه",
    "level": "سهل",
    "source": "غير محدد",
    "q": "من شروط وجوب الحج على المسلم أن يكون:",
    "a": [
      "حافظاً للقرآن",
      "مستطيعاً",
      "متزوجاً",
      "مقيماً في مكة"
    ],
    "c": 1
  },
  {
    "id": 9,
    "category": "فقه",
    "level": "متوسط",
    "source": "غير محدد",
    "q": "إذا دخل وقت الصلاة وكان الماء موجوداً ويستطيع استعماله، فهل يجوز له التيمم؟",
    "a": [
      "يجوز مطلقاً",
      "يجوز في السفر فقط",
      "لا يجوز",
      "يجوز إذا كان مستعجلاً"
    ],
    "c": 2
  },
  {
    "id": 10,
    "category": "فقه",
    "level": "سهل",
    "source": "غير محدد",
    "q": "أي الآتي من نواقض الوضوء باتفاق العلماء؟",
    "a": [
      "لمس المصحف",
      "النوم اليسير",
      "خروج البول",
      "الابتسام في الصلاة"
    ],
    "c": 2
  },
  {
    "id": 11,
    "category": "ثقافة إسلامية",
    "level": "متوسط",
    "source": "غير محدد",
    "q": "ما اسم أول مسجد بني في الإسلام؟",
    "a": [
      "المسجد الحرام",
      "المسجد النبوي",
      "مسجد قباء",
      "المسجد الأقصى"
    ],
    "c": 2
  },
  {
    "id": 12,
    "category": "عقيدة",
    "level": "سهل",
    "source": "غير محدد",
    "q": "ما عدد أركان الإيمان؟",
    "a": [
      "ثلاثة",
      "أربعة",
      "ستة",
      "سبعة"
    ],
    "c": 2
  },
  {
    "id": 13,
    "category": "عقيدة",
    "level": "متوسط",
    "source": "غير محدد",
    "q": "من أركان الإيمان بالله تعالى الإيمان بـ:",
    "a": [
      "أسماؤه الحسنى وصفاته العليا فقط",
      "توحيده وربوبيته وألوهيته",
      "قدره الخير والشر فقط",
      "ملائكته فقط"
    ],
    "c": 1
  },
  {
    "id": 14,
    "category": "عقيدة",
    "level": "صعب",
    "source": "الأصول الثلاثة",
    "q": "ما الأصل الأول من الأصول الثلاثة التي يجب على الإنسان معرفتها؟",
    "a": [
      "معرفة النبي صلى الله عليه وسلم",
      "معرفة دين الإسلام بالأدلة",
      "معرفة العبد ربه",
      "معرفة اليوم الآخر"
    ],
    "c": 2
  },
  {
    "id": 15,
    "category": "عقيدة",
    "level": "صعب",
    "source": "الأصول الثلاثة",
    "q": "بم عرّف الشيخ رحمه الله العبادة؟",
    "a": [
      "كل عمل صالح فقط",
      "اسم جامع لكل ما يحبه الله ويرضاه من الأقوال والأعمال الظاهرة والباطنة",
      "الصلاة والزكاة والصيام فقط",
      "كل ما اعتاده الناس من الطاعات"
    ],
    "c": 1
  },
  {
    "id": 16,
    "category": "عقيدة",
    "level": "صعب",
    "source": "الأصول الثلاثة",
    "q": "ما الدليل الذي استدل به الشيخ على أن الدعاء من أنواع العبادة؟",
    "a": [
      "وقوله تعالى: وأقيموا الصلاة",
      "وقوله تعالى: فاعبد الله مخلصاً له الدين",
      "وقوله تعالى: وأن المساجد لله فلا تدعوا مع الله أحداً",
      "وقوله تعالى: وقل رب زدني علماً"
    ],
    "c": 2
  },
  {
    "id": 17,
    "category": "عقيدة",
    "level": "صعب",
    "source": "الأصول الثلاثة",
    "q": "ما معنى الكفر بالطاغوت كما قرره الشيخ؟",
    "a": [
      "بغض العصاة فقط",
      "ترك المعاصي كلها",
      "أن تكفر بكل ما يعبد من دون الله وتتبرأ منه",
      "عدم التعامل مع غير المسلمين"
    ],
    "c": 2
  },
  {
    "id": 18,
    "category": "عقيدة",
    "level": "صعب",
    "source": "الأصول الثلاثة",
    "q": "كم عدد مراتب دين الإسلام المذكورة في الأصول الثلاثة؟",
    "a": [
      "مرتبتان",
      "ثلاث مراتب",
      "أربع مراتب",
      "خمس مراتب"
    ],
    "c": 1
  },
  {
    "id": 19,
    "category": "عقيدة",
    "level": "صعب",
    "source": "الأصول الثلاثة",
    "q": "أي مما يلي يُعد من أركان الإحسان؟",
    "a": [
      "أن تعبد الله كأنك تراه فإن لم تكن تراه فإنه يراك",
      "الإيمان بالملائكة",
      "إقام الصلاة",
      "الحج إلى بيت الله"
    ],
    "c": 0
  },
  {
    "id": 20,
    "category": "عقيدة",
    "level": "صعب",
    "source": "الأصول الثلاثة",
    "q": "ما أول ما فرض الله على بني آدم كما ذكر الشيخ؟",
    "a": [
      "الصلاة",
      "الصيام",
      "الكفر بالطاغوت والإيمان بالله",
      "الحج"
    ],
    "c": 2
  },
  {
    "id": 21,
    "category": "عقيدة",
    "level": "صعب",
    "source": "الأصول الثلاثة",
    "q": "بم أجاب الشيخ عن السؤال: من نبيك؟",
    "a": [
      "هو محمد بن عبد الله بن عبد المطلب بن هاشم",
      "هو خاتم الأنبياء فقط",
      "هو نبي العرب فقط",
      "هو صاحب المعجزات"
    ],
    "c": 0
  },
  {
    "id": 22,
    "category": "عقيدة",
    "level": "صعب",
    "source": "الأصول الثلاثة",
    "q": "ما معنى الحنيفية التي وصفها الشيخ بأنها ملة إبراهيم؟",
    "a": [
      "الزهد في الدنيا",
      "عبادة الله وحده مخلصاً له الدين",
      "كثرة النوافل",
      "ترك المباحات"
    ],
    "c": 1
  },
  {
    "id": 23,
    "category": "عقيدة",
    "level": "صعب",
    "source": "الأصول الثلاثة",
    "q": "ما المراد بمعرفة النبي ﷺ كما قررها المؤلف في الأصول الثلاثة؟",
    "a": [
      "معرفة نسبه وأسرته فقط",
      "معرفة سيرته وأخلاقه دون رسالته",
      "معرفة اسمه ونسبه وما أُرسل به من التوحيد وطاعته",
      "معرفة حروبه وغزواته فقط"
    ],
    "c": 2
  },
  {
    "id": 24,
    "category": "عقيدة",
    "level": "صعب",
    "source": "الأصول الثلاثة",
    "q": "ما الدليل الذي استدل به المؤلف على وجوب عبادة الله وحده؟",
    "a": [
      "قوله تعالى: قل هو الله أحد",
      "قوله تعالى: وما خلقت الجن والإنس إلا ليعبدون",
      "حديث جبريل عليه السلام",
      "آية الكرسي"
    ],
    "c": 1
  },
  {
    "id": 25,
    "category": "عقيدة",
    "level": "صعب",
    "source": "الأصول الثلاثة",
    "q": "أي مما يلي يدخل في مفهوم العبادة التي لا تصرف إلا لله؟",
    "a": [
      "الخوف من المخلوق فيما يقدر عليه",
      "الرجاء فيما يملك الإنسان",
      "الدعاء والاستغاثة والتوكل",
      "العمل الدنيوي المباح"
    ],
    "c": 2
  },
  {
    "id": 26,
    "category": "عقيدة",
    "level": "صعب",
    "source": "الأصول الثلاثة",
    "q": "ما حكم من صرف نوعاً من أنواع العبادة لغير الله؟",
    "a": [
      "معصية دون أثر على العقيدة",
      "بدعة في العمل فقط",
      "شرك أكبر يناقض أصل التوحيد",
      "خلاف فقهي لا يترتب عليه شيء"
    ],
    "c": 2
  },
  {
    "id": 27,
    "category": "عقيدة",
    "level": "صعب",
    "source": "الأصول الثلاثة",
    "q": "ما معنى الإسلام عند المؤلف في سياق مراتب الدين؟",
    "a": [
      "الاستسلام الظاهري بالأعمال فقط",
      "الاستسلام لله بالتوحيد والانقياد له بالطاعة والبراءة من الشرك",
      "الالتزام بالأخلاق العامة",
      "معرفة الأحكام الشرعية فقط"
    ],
    "c": 1
  },
  {
    "id": 28,
    "category": "عقيدة",
    "level": "صعب",
    "source": "الأصول الثلاثة",
    "q": "ما الفرق بين الإسلام والإيمان كما ورد في حديث جبريل؟",
    "a": [
      "لا فرق بينهما مطلقاً",
      "الإسلام أعمال ظاهرة والإيمان اعتقاد باطن",
      "الإسلام خاص بالأنبياء والإيمان بالعلماء",
      "الإيمان أقل مرتبة من الإسلام"
    ],
    "c": 1
  },
  {
    "id": 29,
    "category": "عقيدة",
    "level": "صعب",
    "source": "الأصول الثلاثة",
    "q": "ما المقصود بالإيمان باليوم الآخر؟",
    "a": [
      "الإيمان بوجود الزمن فقط",
      "الإيمان بالموت دون بعث",
      "الإيمان بالبعث والحساب والجنة والنار",
      "الإيمان بالأحداث الدنيوية المستقبلية"
    ],
    "c": 2
  },
  {
    "id": 30,
    "category": "عقيدة",
    "level": "صعب",
    "source": "الأصول الثلاثة",
    "q": "ما الحكم الشرعي في دعاء غير الله فيما لا يقدر عليه إلا الله؟",
    "a": [
      "جائز إذا كان من باب التوسل",
      "مكروه فقط",
      "شرك أكبر مخرج من الملة",
      "خلاف فقهي معتبر"
    ],
    "c": 2
  },
  {
    "id": 31,
    "category": "فقه",
    "level": "صعب",
    "source": "زاد المستقنع",
    "q": "ما الحكم إذا انقطع تيقن الطهارة عند المتوضئ أثناء الصلاة ثم شك هل أحدث قبلها؟",
    "a": [
      "تبطل صلاته ويجب الإعادة مطلقًا",
      "يبني على اليقين وهو الطهارة السابقة ولا يلتفت للشك",
      "يقطع الصلاة ويتوضأ فورًا",
      "يكمل الصلاة ثم يعيدها احتياطًا"
    ],
    "c": 1
  },
  {
    "id": 32,
    "category": "فقه",
    "level": "صعب",
    "source": "زاد المستقنع",
    "q": "ما الحكم فيمن توضأ ومسح على الخفين ثم خلعهما قبل انتقاض وضوئه؟",
    "a": [
      "ينتقض وضوؤه فورًا",
      "لا ينتقض وضوؤه ما دام لم يحدث",
      "يجب عليه إعادة المسح فقط",
      "تبطل الصلاة فقط دون الوضوء"
    ],
    "c": 1
  },
  {
    "id": 33,
    "category": "فقه",
    "level": "صعب",
    "source": "زاد المستقنع",
    "q": "إذا شك في وصول الماء إلى عضو من أعضاء الوضوء بعد الفراغ منه، فما الحكم؟",
    "a": [
      "يعيد الوضوء كاملًا",
      "يبني على صحة الوضوء ولا يلتفت للشك",
      "يغسل العضو فقط",
      "يعيد الصلاة فقط"
    ],
    "c": 1
  },
  {
    "id": 34,
    "category": "فقه",
    "level": "صعب",
    "source": "زاد المستقنع",
    "q": "ما الحكم إذا مسح على الجبيرة مع وجود ضرر من نزعها؟",
    "a": [
      "لا يجوز المسح ويجب الغسل",
      "يمسح عليها ويجزئ ذلك",
      "يتيمم فقط دون مسح",
      "يجمع بين الغسل والتيمم دائمًا"
    ],
    "c": 1
  },
  {
    "id": 35,
    "category": "فقه",
    "level": "صعب",
    "source": "زاد المستقنع",
    "q": "ما الحكم إذا توضأ ثم خرج منه دم يسير لا ينقض عند الحنابلة؟",
    "a": [
      "ينتقض الوضوء مطلقًا",
      "لا ينقض الوضوء",
      "ينقض إذا كان كثيرًا فقط",
      "ينقض في الصلاة فقط"
    ],
    "c": 1
  },
  {
    "id": 36,
    "category": "فقه",
    "level": "صعب",
    "source": "زاد المستقنع",
    "q": "إذا بدأ المتوضئ باليد اليسرى قبل اليمنى عمدًا، فما الحكم؟",
    "a": [
      "يبطل الوضوء",
      "يصح الوضوء مع الكراهة عند المخالفة",
      "يجب إعادة الوضوء",
      "لا أثر لذلك مطلقًا"
    ],
    "c": 1
  },
  {
    "id": 37,
    "category": "فقه",
    "level": "صعب",
    "source": "زاد المستقنع",
    "q": "ما الحكم إذا زال ماء الوضوء قبل تمام الأعضاء بسبب تبخر أو جفاف شديد؟",
    "a": [
      "يستأنف الوضوء من البداية",
      "يبني على ما سبق",
      "يكمل بلا ماء",
      "يكتفي بالتيمم دائمًا"
    ],
    "c": 0
  },
  {
    "id": 38,
    "category": "فقه",
    "level": "صعب",
    "source": "زاد المستقنع",
    "q": "إذا توضأ بماء طاهر ثم تبين أنه كان نجسًا بعد الصلاة، فما الحكم؟",
    "a": [
      "لا إعادة عليه مطلقًا",
      "يعيد الوضوء والصلاة",
      "يعيد الصلاة فقط دون الوضوء",
      "يكفيه التوبة فقط"
    ],
    "c": 1
  },
  {
    "id": 39,
    "category": "فقه",
    "level": "صعب",
    "source": "زاد المستقنع",
    "q": "ما الحكم فيمن لم يرتب أعضاء الوضوء عمدًا؟",
    "a": [
      "يصح الوضوء بلا ترتيب",
      "يبطل الوضوء عند الحنابلة",
      "يصح مع الكراهة",
      "يعيد غسل الوجه فقط"
    ],
    "c": 1
  },
  {
    "id": 40,
    "category": "فقه",
    "level": "صعب",
    "source": "زاد المستقنع",
    "q": "إذا توضأ ثم نام نوماً خفيفًا دون استغراق، فما الحكم؟",
    "a": [
      "ينتقض الوضوء مطلقًا",
      "لا ينقض الوضوء ما لم يتيقن الحدث",
      "ينقض في جميع الحالات",
      "يبطل الوضوء إذا طال النوم"
    ],
    "c": 1
   },
  {
    "id": 41,
    "category": "فقه",
    "level": "صعب",
    "source": "زاد المستقنع",
    "q": "ما الحكم إذا ترك المصلي تكبيرة الإحرام عمداً ثم دخل في الصلاة؟",
    "a": [
      "تصح صلاته مع سجود السهو",
      "لا تنعقد صلاته أصلًا",
      "تصح الصلاة إذا نوى الدخول",
      "يُعذر بالجهل فقط"
    ],
    "c": 1
  },
  {
    "id": 42,
    "category": "فقه",
    "level": "صعب",
    "source": "زاد المستقنع",
    "q": "إذا سبق المأموم إمامه بركعة كاملة سهواً، فما الحكم؟",
    "a": [
      "تبطل صلاته مطلقًا",
      "تصح مع الإثم فقط",
      "يلزمه الرجوع لمتابعة الإمام وتدارك ما سبق",
      "لا شيء عليه مطلقًا"
    ],
    "c": 2
  },
  {
    "id": 43,
    "category": "فقه",
    "level": "صعب",
    "source": "زاد المستقنع",
    "q": "ما الحكم فيمن تعمد ترك ركن من أركان الصلاة غير تكبيرة الإحرام؟",
    "a": [
      "تصح الصلاة مع السهو",
      "تبطل الصلاة ويجب الإعادة",
      "يُجبر بسجود السهو فقط",
      "تصح إذا كان جاهلًا"
    ],
    "c": 1
  },
  {
    "id": 44,
    "category": "فقه",
    "level": "صعب",
    "source": "زاد المستقنع",
    "q": "إذا نسي المصلي التشهد الأول وقام للركعة الثالثة، ثم تذكر أثناء القيام، فما الحكم عند الحنابلة؟",
    "a": [
      "يرجع للتشهد ما لم يستتم قائمًا",
      "يكمل الصلاة ولا يرجع مطلقًا",
      "تبطل الصلاة",
      "يُعيد الصلاة كاملة"
    ],
    "c": 0
  },
  {
    "id": 45,
    "category": "فقه",
    "level": "صعب",
    "source": "زاد المستقنع",
    "q": "ما حكم ترك الطمأنينة في الركوع أو السجود؟",
    "a": [
      "مكروه فقط",
      "لا يؤثر على صحة الصلاة",
      "ركن تبطل الصلاة بتركه",
      "سنة مستحبة"
    ],
    "c": 2
  },
  {
    "id": 46,
    "category": "فقه",
    "level": "صعب",
    "source": "زاد المستقنع",
    "q": "إذا شك المصلي في عدد الركعات أثناء الصلاة، فما الذي يبني عليه عند الحنابلة؟",
    "a": [
      "يبني على الأقل المتيقن",
      "يبني على الأكثر",
      "يعيد الصلاة",
      "يستمر بلا اعتبار للشك"
    ],
    "c": 0
  },
  {
    "id": 47,
    "category": "فقه",
    "level": "صعب",
    "source": "زاد المستقنع",
    "q": "ما الحكم إذا أحدث الإمام أثناء الصلاة ولم يستخلف أحداً؟",
    "a": [
      "تتم صلاة المأمومين منفردين",
      "تبطل صلاة الجميع",
      "تستمر الصلاة بلا إمام",
      "تُعاد الصلاة فقط للإمام"
    ],
    "c": 1
  },
  {
    "id": 48,
    "category": "فقه",
    "level": "صعب",
    "source": "زاد المستقنع",
    "q": "إذا زاد المصلي ركعة عمداً في الصلاة، فما الحكم؟",
    "a": [
      "تصح مع سجود السهو",
      "تبطل الصلاة",
      "تصح إذا كان جاهلاً",
      "تجبر بسجود السهو فقط"
    ],
    "c": 1
  },
  {
    "id": 49,
    "category": "فقه",
    "level": "صعب",
    "source": "زاد المستقنع",
    "q": "ما الحكم فيمن ترك قراءة الفاتحة عمداً في الصلاة؟",
    "a": [
      "تصح الصلاة مع الإثم",
      "تبطل الصلاة",
      "تجبر بسجود السهو",
      "تصح إذا قرأ غيرها"
    ],
    "c": 1
  },
  {
    "id": 50,
    "category": "فقه",
    "level": "صعب",
    "source": "زاد المستقنع",
    "q": "إذا دخل وقت الصلاة ثم نام الشخص حتى خرج الوقت دون عذر، فما الحكم؟",
    "a": [
      "قضاء الصلاة فقط دون إثم",
      "إثم مع وجوب القضاء",
      "لا قضاء عليه",
      "تصح الصلاة إذا نواها قبل النوم"
    ],
    "c": 1
  }
]
